irspack/definitions.py
irspack/_version.py
irspack/__init__.py
irspack/_threading.py
irspack/default_logger.py
irspack/split/time.py
irspack/split/__init__.py
irspack/split/specified.py
irspack/split/userwise.py
irspack/dataset/citeulike.py
irspack/dataset/downloader.py
irspack/dataset/neu_mf.py
irspack/dataset/amazon_music.py
irspack/dataset/__init__.py
irspack/dataset/movielens/ML100K.py
irspack/dataset/movielens/__init__.py
irspack/dataset/movielens/ML20M.py
irspack/dataset/movielens/base.py
irspack/dataset/movielens/ML1M.py
irspack/optimization/parameter_range.py
irspack/optimization/__init__.py
irspack/optimization/optimizer.py
irspack/utils/__init__.py
irspack/utils/random.py
irspack/utils/id_mapping.py
irspack/utils/sample_data.py
irspack/utils/_util_cpp.cpython-311-darwin.so
irspack/utils/_util_cpp.pyi
irspack/recommenders/_knn.pyi
irspack/recommenders/truncsvd.py
irspack/recommenders/__init__.py
irspack/recommenders/rp3.py
irspack/recommenders/user_knn.py
irspack/recommenders/edlae.py
irspack/recommenders/slim.py
irspack/recommenders/base_earlystop.py
irspack/recommenders/toppop.py
irspack/recommenders/dense_slim.py
irspack/recommenders/bpr.py
irspack/recommenders/_ials_core.cpython-311-darwin.so
irspack/recommenders/_knn.cpython-311-darwin.so
irspack/recommenders/p3.py
irspack/recommenders/multvae.py
irspack/recommenders/nmf.py
irspack/recommenders/base.py
irspack/recommenders/_ials_core.pyi
irspack/recommenders/ials.py
irspack/recommenders/knn.py
irspack/evaluation/__init__.py
irspack/evaluation/evaluate_df_to_df.py
irspack/evaluation/_core_evaluator.pyi
irspack/evaluation/evaluator.py
irspack/evaluation/_core_evaluator.cpython-311-darwin.so
irspack-0.4.0.dist-info/RECORD
irspack-0.4.0.dist-info/WHEEL
irspack-0.4.0.dist-info/METADATA
irspack-0.4.0.dist-info/licenses/LICENSE
