Metadata-Version: 2.4
Name: irspack
Version: 0.4.0
Summary: Implicit feedback-based recommender systems, packed for practitioners.
Author-Email: Tomoki Ohtsuki <tomoki.ohtsuki.19937@outlook.jp>
License-Expression: MIT
Project-URL: Homepage, https://github.com/tohtsky/irspack
Requires-Dist: httpx
Requires-Dist: gidgethub[httpx]>4.0.0
Requires-Dist: numpy>=2.0
Requires-Dist: fastprogress>=0.2
Requires-Dist: optuna>=2.5.0
Requires-Dist: pandas>=2.2.0
Requires-Dist: scikit-learn>=0.21.0
Requires-Dist: scipy>=1.0
Requires-Dist: colorlog>=4
Requires-Dist: pydantic>=2.0
